{
    "bank": {
        "name": "MEMBERS PLUS C.U.", 
        "phone": "(866) 306-6728", 
        "url": "www.memberspluscu.org"
    }, 
    "brand": "Traditional", 
    "country": {
        "alpha2": "US", 
        "currency": "USD", 
        "emoji": "\ud83c\uddfa\ud83c\uddf8", 
        "latitude": 38, 
        "longitude": -97, 
        "name": "United States of America", 
        "numeric": "840"
    }, 
    "number": {
        "length": 16, 
        "luhn": true
    }, 
    "prepaid": false, 
    "scheme": "visa", 
    "type": "debit"
}